token_distance/__init__.py
token_distance/algorithms/__init__.py
token_distance/algorithms/token_distance.py
token_distance/algorithms/token_matching.py
token_distance/means/__init__.py
token_distance/means/base.py
token_distance/similarities/__init__.py
token_distance/similarities/base.py
token_distance/types/__init__.py
token_distance/types/registry.py
token_distance/types/token.py
token_distance/ui/__init__.py
token_distance/ui/console.py
token_distance/weights/__init__.py
token_distance/weights/common.py
token_distance-0.2.5.dist-info/LICENSE
token_distance-0.2.5.dist-info/METADATA
token_distance-0.2.5.dist-info/WHEEL
token_distance-0.2.5.dist-info/entry_points.txt
token_distance-0.2.5.dist-info/RECORD
