Metadata-Version: 2.3
Name: token-distance
Version: 0.2.5
Summary: Python library designed to perform fuzzy token matching within text documents. Utilizing advanced algorithms, this tool allows developers and data scientists to search and compare tokens based on flexible criteria, beyond exact matches. The library supports tokenization through whitespace, regular expressions, or custom functions, and provides weighted comparisons for nuanced analysis.
License: BSD
Keywords: fuzzy match,search
Author: voidpointercast
Author-email: voidpointercast@justmail.de
Requires-Python: >=3.10,<4.0
Classifier: Development Status :: 4 - Beta
Classifier: Environment :: Console
Classifier: Intended Audience :: End Users/Desktop
Classifier: Intended Audience :: Science/Research
Classifier: Intended Audience :: System Administrators
Classifier: License :: OSI Approved :: BSD License
Classifier: License :: Other/Proprietary License
Classifier: Operating System :: POSIX :: Linux
Classifier: Programming Language :: Python :: 3
Classifier: Programming Language :: Python :: 3.10
Classifier: Programming Language :: Python :: 3.11
Classifier: Programming Language :: Python :: 3.12
Classifier: Programming Language :: Python :: 3.13
Classifier: Topic :: Scientific/Engineering :: Information Analysis
Classifier: Topic :: Text Processing :: Filters
Requires-Dist: jellyfish (>=1.0.3,<2.0.0)
Project-URL: Documentation, https://token-distance.readthedocs.io/en/latest/
Project-URL: Homepage, https://gitlab.com/patrick.daniel.gress/token-distance
Project-URL: Repository, https://gitlab.com/patrick.daniel.gress/token-distance
